Metadata-Version: 1.0
Name: rule-servant-pizzani
Version: 3.5
Summary: Rule Servant
Home-page: UNKNOWN
Author: Bruno Pizzani Mendoza
Author-email: UNKNOWN
License: UNKNOWN
Platform: UNKNOWN
